LICENSE
MANIFEST.in
README.rst
mongoify.py
setup.py
django_heroku_mongoify.egg-info/PKG-INFO
django_heroku_mongoify.egg-info/SOURCES.txt
django_heroku_mongoify.egg-info/dependency_links.txt
django_heroku_mongoify.egg-info/top_level.txt
tests/test_mongoify.py