Metadata-Version: 1.0
Name: django-heroku-mongoify
Version: 0.1.0
Summary: Friendly MongoDB for Django on Heroku
Home-page: https://github.com/dirn/django-heroku-mongoify
Author: Andy Dirnberger
Author-email: dirn@dirnonline.com
License: Copyright (c) 2012, Andy Dirnberger
